gwrapper/__init__.py
gwrapper/logger_interface.py
gwrapper/number_filter.py
gwrapper/string_filter.py
gwrapper/wrapper.py
gwrapper/schemas/wrapper_schema.json
prfilterutility-0.0.8.dist-info/LICENSE
prfilterutility-0.0.8.dist-info/METADATA
prfilterutility-0.0.8.dist-info/WHEEL
prfilterutility-0.0.8.dist-info/top_level.txt
prfilterutility-0.0.8.dist-info/RECORD
