Metadata-Version: 2.1
Name: prfilterutility
Version: 0.0.8
Summary: Package to provide utility tools for Github Pull Requests
Home-page: https://github.com/oakbani/f3Github/gwrapper
Author: Mariam Jamal
Author-email: mjamal@folio3.com
License: UNKNOWN
Platform: UNKNOWN
Classifier: License :: OSI Approved :: MIT License
Classifier: Operating System :: OS Independent
Classifier: Programming Language :: Python
Classifier: Programming Language :: Python :: 3.5
Classifier: Programming Language :: Python :: 3.6
